<?xml version = '1.0' encoding = 'UTF-8'?>
<FKIndexAssociation class="oracle.dbtools.crest.model.design.relational.FKIndexAssociation" directorySegmentName="seg_0" id="2F141ECA-562F-CD6D-958A-76F4BAD95D80" containerWithKeyObject="12A57808-65A3-A4E6-421D-250D2DD1F3FA" localFKIndex="7FD1E5C9-7A61-B8CD-F3B4-07B0C0D862BF" name="HOSPITAL_MEDICO_FK2">
<sourceConnName>work</sourceConnName>
<sourceObjSchema>USER1</sourceObjSchema>
<sourceObjName>HOSPITAL_MEDICO_FK2</sourceObjName>
<createdBy>adriana</createdBy>
<createdTime>2017-11-23 14:49:07 UTC</createdTime>
<ownerDesignName>relational</ownerDesignName>
<importedID>60BCD696-08F5-9875-DDD2-7E1F5BA5641E</importedID>
<referredTableLongName>USER1.MEDICO</referredTableLongName>
<deleteRule>NO ACTION</deleteRule>
<referredTableID>198A2D09-8F99-7B07-A232-E8168C13DFE8</referredTableID>
<keyObject>F43481F2-83EF-F7F3-490F-3EC1106891B8</keyObject>
<referredKeyID>F43481F2-83EF-F7F3-490F-3EC1106891B8</referredKeyID>
<mandatory>true</mandatory>
<refColNames>ID_MEDICO</refColNames>
<transferable>true</transferable>
<rely>false</rely>
<columnDependencyConstraintGenerateInDDL>true</columnDependencyConstraintGenerateInDDL>
</FKIndexAssociation>